<?xml version="1.0" encoding="utf-8"?><mapa aprid="mapa">
  <copyright>(c) Editorial Planeta</copyright>
  <version>1.0</version>
  <botonMapaConceptual>mostrar</botonMapaConceptual>
  <botonMapaMudo>ocultar</botonMapaMudo>
  <botonMudo>0</botonMudo>
  <objeto>
    <ref>00</ref>
    <texto>Las ondas estacionarias</texto>
    <hijos>10,11,12</hijos>
    <padre/>
    <siz>0</siz>
    <negcur>00000000000000000000000</negcur>
    <cen>1</cen>
    <img/>
    <audio/>
  </objeto>
  <objeto>
    <ref>10</ref>
    <texto>se forman por</texto>
    <hijos>20</hijos>
    <padre>00</padre>
    <siz>14</siz>
    <negcur>0000000000000</negcur>
    <cen>1</cen>
    <img/>
    <audio/>
  </objeto>
  <objeto>
    <ref>20</ref>
    <texto>Interferencia</texto>
    <hijos>30</hijos>
    <padre>10</padre>
    <siz>0</siz>
    <negcur>0000000000000</negcur>
    <cen>1</cen>
    <img/>
    <audio/>
  </objeto>
  <objeto>
    <ref>11</ref>
    <texto>son la base de</texto>
    <hijos>21</hijos>
    <padre>00</padre>
    <siz>0</siz>
    <negcur>00000000000000</negcur>
    <cen>1</cen>
    <img/>
    <audio/>
  </objeto>
  <objeto>
    <ref>21</ref>
    <texto>La música</texto>
    <hijos>31,32,33</hijos>
    <padre>11</padre>
    <siz>0</siz>
    <negcur>000000000</negcur>
    <cen>1</cen>
    <img/>
    <audio/>
  </objeto>
  <objeto>
    <ref>12</ref>
    <texto>se observan en</texto>
    <hijos>22,23</hijos>
    <padre>00</padre>
    <siz>0</siz>
    <negcur>00000000000000</negcur>
    <cen>1</cen>
    <img/>
    <audio/>
  </objeto>
  <objeto>
    <ref>22</ref>
    <texto>Cuerdas</texto>
    <hijos>34</hijos>
    <padre>12</padre>
    <siz>0</siz>
    <negcur>0000000</negcur>
    <cen>1</cen>
    <img/>
    <audio/>
  </objeto>
  <objeto>
    <ref>30</ref>
    <texto>de</texto>
    <hijos>40</hijos>
    <padre>20</padre>
    <siz>0</siz>
    <negcur>00</negcur>
    <cen>1</cen>
    <img/>
    <audio/>
  </objeto>
  <objeto>
    <ref>40</ref>
    <texto>ondas con igual
amplitud y frecuencia
pero dirección opuesta</texto>
    <hijos>50</hijos>
    <padre>30</padre>
    <siz>0</siz>
    <negcur>000000000000000000000000000000000000000000000000000000000000</negcur>
    <cen>1</cen>
    <img/>
    <audio/>
  </objeto>
  <objeto>
    <ref>50</ref>
    <texto>pueden formarse
entre ondas</texto>
    <hijos>60</hijos>
    <padre>40</padre>
    <siz>0</siz>
    <negcur>000000000000000000000000000</negcur>
    <cen>1</cen>
    <img/>
    <audio/>
  </objeto>
  <objeto>
    <ref>60</ref>
    <texto>- longitudinales
- transversales</texto>
    <hijos/>
    <padre>50</padre>
    <siz>0</siz>
    <negcur>00000000000000000000000000000000</negcur>
    <cen>0</cen>
    <img/>
    <audio/>
  </objeto>
  <objeto>
    <ref>31</ref>
    <texto>se compone de</texto>
    <hijos>41</hijos>
    <padre>21</padre>
    <siz>0</siz>
    <negcur>0000000000000</negcur>
    <cen>1</cen>
    <img/>
    <audio/>
  </objeto>
  <objeto>
    <ref>41</ref>
    <texto>sonidos
musicales</texto>
    <hijos>51</hijos>
    <padre>31</padre>
    <siz>0</siz>
    <negcur>00000000000000000</negcur>
    <cen>1</cen>
    <img/>
    <audio/>
  </objeto>
  <objeto>
    <ref>32</ref>
    <texto>son producidos por</texto>
    <hijos>42</hijos>
    <padre>21</padre>
    <siz>0</siz>
    <negcur>000000000000000000</negcur>
    <cen>1</cen>
    <img/>
    <audio/>
  </objeto>
  <objeto>
    <ref>42</ref>
    <texto>instrumentos
musicales</texto>
    <hijos>52</hijos>
    <padre>32</padre>
    <siz>0</siz>
    <negcur>0000000000000000000000</negcur>
    <cen>1</cen>
    <img/>
    <audio/>
  </objeto>
  <objeto>
    <ref>33</ref>
    <texto>gracias a</texto>
    <hijos>43</hijos>
    <padre>21</padre>
    <siz>0</siz>
    <negcur>000000000</negcur>
    <cen>1</cen>
    <img/>
    <audio/>
  </objeto>
  <objeto>
    <ref>43</ref>
    <texto>la regularidad
que presentan</texto>
    <hijos/>
    <padre>33</padre>
    <siz>0</siz>
    <negcur>0000000000000000000000000000</negcur>
    <cen>1</cen>
    <img/>
    <audio/>
  </objeto>
  <objeto>
    <ref>51</ref>
    <texto>que presentan</texto>
    <hijos>61,62,63</hijos>
    <padre>41</padre>
    <siz>0</siz>
    <negcur>0000000000000</negcur>
    <cen>1</cen>
    <img/>
    <audio/>
  </objeto>
  <objeto>
    <ref>61</ref>
    <texto>altura</texto>
    <hijos>70</hijos>
    <padre>51</padre>
    <siz>0</siz>
    <negcur>000000</negcur>
    <cen>1</cen>
    <img/>
    <audio/>
  </objeto>
  <objeto>
    <ref>62</ref>
    <texto>intensidad</texto>
    <hijos>71</hijos>
    <padre>51</padre>
    <siz>0</siz>
    <negcur>0000000000</negcur>
    <cen>1</cen>
    <img/>
    <audio/>
  </objeto>
  <objeto>
    <ref>63</ref>
    <texto>timbre</texto>
    <hijos>72</hijos>
    <padre>51</padre>
    <siz>0</siz>
    <negcur>000000</negcur>
    <cen>1</cen>
    <img/>
    <audio/>
  </objeto>
  <objeto>
    <ref>70</ref>
    <texto>determinada por</texto>
    <hijos>80</hijos>
    <padre>61</padre>
    <siz>0</siz>
    <negcur>000000000000000</negcur>
    <cen>1</cen>
    <img/>
    <audio/>
  </objeto>
  <objeto>
    <ref>80</ref>
    <texto>la cantidad, tipo
e intensidad de
los sobretonos</texto>
    <hijos/>
    <padre>70</padre>
    <siz>0</siz>
    <negcur>000000000000000000000000000000000000000000000000</negcur>
    <cen>1</cen>
    <img/>
    <audio/>
  </objeto>
  <objeto>
    <ref>71</ref>
    <texto>determinada por</texto>
    <hijos>81</hijos>
    <padre>62</padre>
    <siz>0</siz>
    <negcur>000000000000000</negcur>
    <cen>1</cen>
    <img/>
    <audio/>
  </objeto>
  <objeto>
    <ref>81</ref>
    <texto>la amplitud
de la onda</texto>
    <hijos/>
    <padre>71</padre>
    <siz>0</siz>
    <negcur>0000000000000000000000</negcur>
    <cen>1</cen>
    <img/>
    <audio/>
  </objeto>
  <objeto>
    <ref>72</ref>
    <texto>determinada por</texto>
    <hijos>82</hijos>
    <padre>63</padre>
    <siz>0</siz>
    <negcur>000000000000000</negcur>
    <cen>1</cen>
    <img/>
    <audio/>
  </objeto>
  <objeto>
    <ref>82</ref>
    <texto>la frecuencia
de la onda</texto>
    <hijos/>
    <padre>72</padre>
    <siz>0</siz>
    <negcur>000000000000000000000000</negcur>
    <cen>1</cen>
    <img/>
    <audio/>
  </objeto>
  <objeto>
    <ref>52</ref>
    <texto>pueden ser</texto>
    <hijos>64,65,66</hijos>
    <padre>42</padre>
    <siz>0</siz>
    <negcur>0000000000</negcur>
    <cen>1</cen>
    <img/>
    <audio/>
  </objeto>
  <objeto>
    <ref>64</ref>
    <texto>de percusión</texto>
    <hijos>73</hijos>
    <padre>52</padre>
    <siz>0</siz>
    <negcur>000000000000</negcur>
    <cen>1</cen>
    <img/>
    <audio/>
  </objeto>
  <objeto>
    <ref>65</ref>
    <texto>de cuerdas</texto>
    <hijos>74</hijos>
    <padre>52</padre>
    <siz>0</siz>
    <negcur>0000000000</negcur>
    <cen>1</cen>
    <img/>
    <audio/>
  </objeto>
  <objeto>
    <ref>66</ref>
    <texto>de viento</texto>
    <hijos>75,76,77</hijos>
    <padre>52</padre>
    <siz>0</siz>
    <negcur>000000000</negcur>
    <cen>1</cen>
    <img/>
    <audio/>
  </objeto>
  <objeto>
    <ref>73</ref>
    <texto>producen</texto>
    <hijos>83,84</hijos>
    <padre>64</padre>
    <siz>0</siz>
    <negcur>00000000</negcur>
    <cen>1</cen>
    <img/>
    <audio/>
  </objeto>
  <objeto>
    <ref>83</ref>
    <texto>ruido con ritmo</texto>
    <hijos/>
    <padre>73</padre>
    <siz>0</siz>
    <negcur>000000000000000</negcur>
    <cen>1</cen>
    <img/>
    <audio/>
  </objeto>
  <objeto>
    <ref>84</ref>
    <texto>ondas estacionarias
transversales planas</texto>
    <hijos/>
    <padre>73</padre>
    <siz>0</siz>
    <negcur>0000000000000000000000000000000000000000</negcur>
    <cen>1</cen>
    <img/>
    <audio/>
  </objeto>
  <objeto>
    <ref>74</ref>
    <texto>producen</texto>
    <hijos>85</hijos>
    <padre>65</padre>
    <siz>0</siz>
    <negcur>00000000</negcur>
    <cen>1</cen>
    <img/>
    <audio/>
  </objeto>
  <objeto>
    <ref>85</ref>
    <texto>ondas
estacionarias
transversales</texto>
    <hijos/>
    <padre>74</padre>
    <siz>0</siz>
    <negcur>000000000000000000000000000000000</negcur>
    <cen>1</cen>
    <img/>
    <audio/>
  </objeto>
  <objeto>
    <ref>75</ref>
    <texto>funcionan con</texto>
    <hijos>86</hijos>
    <padre>66</padre>
    <siz>0</siz>
    <negcur>0000000000000</negcur>
    <cen>1</cen>
    <img/>
    <audio/>
  </objeto>
  <objeto>
    <ref>86</ref>
    <texto>tubos en donde
se producen
las ondas</texto>
    <hijos/>
    <padre>75</padre>
    <siz>0</siz>
    <negcur>000000000000000000000000000000000000</negcur>
    <cen>1</cen>
    <img/>
    <audio/>
  </objeto>
  <objeto>
    <ref>76</ref>
    <texto>incluyen</texto>
    <hijos>87</hijos>
    <padre>66</padre>
    <siz>0</siz>
    <negcur>00000000</negcur>
    <cen>1</cen>
    <img/>
    <audio/>
  </objeto>
  <objeto>
    <ref>87</ref>
    <texto>la voz
humana</texto>
    <hijos/>
    <padre>76</padre>
    <siz>0</siz>
    <negcur>0000000000000</negcur>
    <cen>1</cen>
    <img/>
    <audio/>
  </objeto>
  <objeto>
    <ref>77</ref>
    <texto>producen</texto>
    <hijos>88</hijos>
    <padre>66</padre>
    <siz>0</siz>
    <negcur>00000000</negcur>
    <cen>1</cen>
    <img/>
    <audio/>
  </objeto>
  <objeto>
    <ref>88</ref>
    <texto>ondas
estacionarias
longitudinales</texto>
    <hijos/>
    <padre>77</padre>
    <siz>0</siz>
    <negcur>0000000000000000000000000000000000</negcur>
    <cen>1</cen>
    <img/>
    <audio/>
  </objeto>
  <objeto>
    <ref>23</ref>
    <texto>Tubos</texto>
    <hijos>35</hijos>
    <padre>12</padre>
    <siz>0</siz>
    <negcur>00000</negcur>
    <cen>1</cen>
    <img/>
    <audio/>
  </objeto>
  <objeto>
    <ref>34</ref>
    <texto>en donde</texto>
    <hijos>44,45</hijos>
    <padre>22</padre>
    <siz>0</siz>
    <negcur>00000000</negcur>
    <cen>1</cen>
    <img/>
    <audio/>
  </objeto>
  <objeto>
    <ref>44</ref>
    <texto>longitudes
de onda</texto>
    <hijos>55</hijos>
    <padre>34</padre>
    <siz>0</siz>
    <negcur>000000000000000000</negcur>
    <cen>1</cen>
    <img/>
    <audio/>
  </objeto>
  <objeto>
    <ref>45</ref>
    <texto>frecuencia
o nodos</texto>
    <hijos>56</hijos>
    <padre>34</padre>
    <siz>0</siz>
    <negcur>000000000000000000</negcur>
    <cen>1</cen>
    <img/>
    <audio/>
  </objeto>
  <objeto>
    <ref>35</ref>
    <texto>pueden ser</texto>
    <hijos>46,47</hijos>
    <padre>23</padre>
    <siz>0</siz>
    <negcur>0000000000</negcur>
    <cen>1</cen>
    <img/>
    <audio/>
  </objeto>
  <objeto>
    <ref>46</ref>
    <texto>abiertos</texto>
    <hijos>53</hijos>
    <padre>35</padre>
    <siz>0</siz>
    <negcur>00000000</negcur>
    <cen>1</cen>
    <img/>
    <audio/>
  </objeto>
  <objeto>
    <ref>47</ref>
    <texto>cerrados</texto>
    <hijos>54</hijos>
    <padre>35</padre>
    <siz>0</siz>
    <negcur>00000000</negcur>
    <cen>1</cen>
    <img/>
    <audio/>
  </objeto>
  <objeto>
    <ref>53</ref>
    <texto>en donde</texto>
    <hijos>67,68</hijos>
    <padre>46</padre>
    <siz>0</siz>
    <negcur>00000000</negcur>
    <cen>1</cen>
    <img/>
    <audio/>
  </objeto>
  <objeto>
    <ref>67</ref>
    <texto>frecuencia 
o nodos</texto>
    <hijos>79</hijos>
    <padre>53</padre>
    <siz>0</siz>
    <negcur>0000000000000000000</negcur>
    <cen>1</cen>
    <img/>
    <audio/>
  </objeto>
  <objeto>
    <ref>68</ref>
    <texto>longitudes
de onda</texto>
    <hijos>78</hijos>
    <padre>53</padre>
    <siz>0</siz>
    <negcur>000000000000000000</negcur>
    <cen>1</cen>
    <img/>
    <audio/>
  </objeto>
  <objeto>
    <ref>54</ref>
    <texto>en donde</texto>
    <hijos>69,6A</hijos>
    <padre>47</padre>
    <siz>0</siz>
    <negcur>00000000</negcur>
    <cen>1</cen>
    <img/>
    <audio/>
  </objeto>
  <objeto>
    <ref>69</ref>
    <texto>frecuencias
o armónicos</texto>
    <hijos>7A</hijos>
    <padre>54</padre>
    <siz>0</siz>
    <negcur>00000000000000000000000</negcur>
    <cen>1</cen>
    <img/>
    <audio/>
  </objeto>
  <objeto>
    <ref>6A</ref>
    <texto>longitudes
de onda</texto>
    <hijos>7B</hijos>
    <padre>54</padre>
    <siz>0</siz>
    <negcur>000000000000000000</negcur>
    <cen>1</cen>
    <img/>
    <audio/>
  </objeto>
  <objeto>
    <ref>55</ref>
    <texto/>
    <hijos>6B</hijos>
    <padre>44</padre>
    <siz>0</siz>
    <negcur/>
    <cen>1</cen>
    <img/>
    <audio/>
  </objeto>
  <objeto>
    <ref>6B</ref>
    <texto/>
    <hijos/>
    <padre>55</padre>
    <siz>0</siz>
    <negcur/>
    <cen>1</cen>
    <img>CN_11_05_CO_formula_mapa_01.png</img>
    <audio/>
  </objeto>
  <objeto>
    <ref>56</ref>
    <texto/>
    <hijos>6C</hijos>
    <padre>45</padre>
    <siz>0</siz>
    <negcur/>
    <cen>1</cen>
    <img/>
    <audio/>
  </objeto>
  <objeto>
    <ref>6C</ref>
    <texto/>
    <hijos/>
    <padre>56</padre>
    <siz>0</siz>
    <negcur/>
    <cen>1</cen>
    <img>CN_11_05_CO_formula_mapa_02.png</img>
    <audio/>
  </objeto>
  <objeto>
    <ref>78</ref>
    <texto/>
    <hijos>89</hijos>
    <padre>68</padre>
    <siz>0</siz>
    <negcur/>
    <cen>1</cen>
    <img/>
    <audio/>
  </objeto>
  <objeto>
    <ref>89</ref>
    <texto/>
    <hijos/>
    <padre>78</padre>
    <siz>0</siz>
    <negcur/>
    <cen>1</cen>
    <img>CN_11_05_CO_formula_mapa_03.png</img>
    <audio/>
  </objeto>
  <objeto>
    <ref>79</ref>
    <texto/>
    <hijos>8A</hijos>
    <padre>67</padre>
    <siz>0</siz>
    <negcur/>
    <cen>1</cen>
    <img/>
    <audio/>
  </objeto>
  <objeto>
    <ref>8A</ref>
    <texto/>
    <hijos/>
    <padre>79</padre>
    <siz>0</siz>
    <negcur/>
    <cen>1</cen>
    <img>CN_11_05_CO_formula_mapa_04.png</img>
    <audio/>
  </objeto>
  <objeto>
    <ref>7A</ref>
    <texto/>
    <hijos>8B</hijos>
    <padre>69</padre>
    <siz>0</siz>
    <negcur/>
    <cen>1</cen>
    <img/>
    <audio/>
  </objeto>
  <objeto>
    <ref>8B</ref>
    <texto/>
    <hijos/>
    <padre>7A</padre>
    <siz>0</siz>
    <negcur/>
    <cen>1</cen>
    <img>CN_11_05_CO_formula_mapa_05.png</img>
    <audio/>
  </objeto>
  <objeto>
    <ref>7B</ref>
    <texto/>
    <hijos>8C</hijos>
    <padre>6A</padre>
    <siz>0</siz>
    <negcur/>
    <cen>1</cen>
    <img/>
    <audio/>
  </objeto>
  <objeto>
    <ref>8C</ref>
    <texto/>
    <hijos/>
    <padre>7B</padre>
    <siz>0</siz>
    <negcur/>
    <cen>1</cen>
    <img>CN_11_05_CO_formula_mapa_06.png</img>
    <audio/>
  </objeto>
</mapa>